[
    {
        "images": [
            16,
            19,
            21,
            39,
            41,
            60,
            63,
            64,
            74,
            80,
            81,
            90,
            93,
            102,
            118,
            128,
            165,
            166,
            174,
            175,
            187,
            209,
            227,
            233,
            238,
            240,
            246,
            253,
            260,
            261,
            268,
            271,
            278,
            288,
            297,
            311,
            334,
            353,
            379,
            382,
            390,
            392,
            394,
            404,
            411,
            416,
            425
        ],
        "centroid": [
            -0.06318106382978722,
            -0.5593953191489363
        ],
        "img": "0-7a82469b-c576-4eec-a033-6ab08a61c0ec.jpg",
        "label": "Cluster 1"
    },
    {
        "images": [
            1,
            2,
            3,
            6,
            28,
            36,
            50,
            61,
            127,
            129,
            146,
            161,
            186,
            192,
            207,
            211,
            212,
            221,
            229,
            237,
            244,
            248,
            251,
            254,
            256,
            279,
            282,
            286,
            293,
            306,
            307,
            321,
            322,
            324,
            330,
            332,
            335,
            343,
            378,
            391,
            399,
            403,
            418,
            440,
            445,
            447
        ],
        "centroid": [
            0.1343326086956522,
            0.5471484782608695
        ],
        "img": "2-0df28659-d5ea-40d1-a9f9-5766b0fdda78.jpg",
        "label": "Cluster 2"
    },
    {
        "images": [
            40,
            49,
            55,
            59,
            65,
            100,
            114,
            132,
            133,
            144,
            160,
            196,
            213,
            216,
            225,
            232,
            234,
            241,
            245,
            258,
            265,
            274,
            291,
            303,
            326,
            329,
            336,
            341,
            351,
            356,
            367,
            370,
            375,
            384,
            388,
            396,
            400,
            413,
            421,
            427,
            430,
            433,
            443
        ],
        "centroid": [
            -0.18678186046511627,
            0.8121253488372095
        ],
        "img": "1-cddbac15_original.jpg",
        "label": "Cluster 3"
    },
    {
        "images": [
            11,
            13,
            18,
            25,
            52,
            54,
            68,
            89,
            94,
            104,
            112,
            119,
            124,
            131,
            140,
            151,
            162,
            164,
            171,
            181,
            185,
            191,
            210,
            217,
            247,
            250,
            255,
            269,
            272,
            275,
            276,
            281,
            292,
            313,
            339,
            349,
            352,
            357,
            363,
            376,
            395,
            438
        ],
        "centroid": [
            0.8031902380952379,
            -0.6391383333333334
        ],
        "img": "1-93dbfbd5_original.jpg",
        "label": "Cluster 4"
    },
    {
        "images": [
            10,
            42,
            43,
            103,
            110,
            117,
            138,
            147,
            168,
            176,
            188,
            190,
            195,
            197,
            199,
            200,
            205,
            219,
            223,
            252,
            257,
            262,
            283,
            284,
            299,
            301,
            304,
            327,
            333,
            337,
            342,
            355,
            387,
            401,
            408,
            414,
            423,
            432,
            435,
            439
        ],
        "centroid": [
            0.40875225000000004,
            -0.82297425
        ],
        "img": "0-ee8e476b_original.jpg",
        "label": "Cluster 5"
    },
    {
        "images": [
            4,
            17,
            46,
            58,
            73,
            77,
            111,
            123,
            126,
            130,
            135,
            139,
            150,
            152,
            172,
            178,
            189,
            206,
            208,
            242,
            263,
            267,
            270,
            290,
            302,
            314,
            316,
            319,
            320,
            323,
            325,
            358,
            373,
            397,
            412,
            417,
            420,
            431
        ],
        "centroid": [
            -0.34767210526315795,
            0.3876078947368421
        ],
        "img": "0-040203a3_original.jpg",
        "label": "Cluster 6"
    },
    {
        "images": [
            0,
            29,
            31,
            35,
            44,
            45,
            51,
            53,
            62,
            72,
            76,
            78,
            85,
            86,
            98,
            99,
            101,
            106,
            108,
            142,
            158,
            184,
            198,
            214,
            259,
            273,
            298,
            308,
            312,
            317,
            338,
            350,
            406,
            419,
            449
        ],
        "centroid": [
            -0.4702665714285715,
            -0.7843545714285715
        ],
        "img": "0-78e9541d_original.jpg",
        "label": "Cluster 7"
    },
    {
        "images": [
            20,
            26,
            27,
            34,
            69,
            70,
            71,
            75,
            82,
            91,
            92,
            105,
            115,
            116,
            125,
            145,
            155,
            169,
            193,
            201,
            218,
            228,
            239,
            280,
            318,
            331,
            344,
            354,
            374,
            380,
            398,
            407,
            441,
            442,
            446
        ],
        "centroid": [
            -0.734514,
            0.4986697142857143
        ],
        "img": "0-ab5039c5-77f4-4100-8612-ff783a9c7128.jpg",
        "label": "Cluster 8"
    },
    {
        "images": [
            7,
            8,
            12,
            24,
            30,
            121,
            137,
            141,
            153,
            156,
            167,
            173,
            179,
            180,
            194,
            203,
            220,
            231,
            235,
            243,
            277,
            287,
            295,
            305,
            328,
            347,
            348,
            365,
            369,
            372,
            402,
            405,
            415,
            437
        ],
        "centroid": [
            0.5014791176470589,
            -0.18861882352941178
        ],
        "img": "0-d59a6e91-a0b6-4e1b-afe8-4f9b902e7655.jpg",
        "label": "Cluster 9"
    },
    {
        "images": [
            9,
            23,
            38,
            47,
            67,
            107,
            113,
            134,
            148,
            154,
            157,
            159,
            163,
            170,
            183,
            215,
            222,
            226,
            230,
            236,
            266,
            300,
            310,
            345,
            361,
            362,
            364,
            377,
            386,
            393,
            426,
            436
        ],
        "centroid": [
            -0.144009375,
            0.0530346875
        ],
        "img": "0-3271e217_original.jpg",
        "label": "Cluster 10"
    }
]